mcp_reticle/__init__.py
mcp_reticle/__main__.py
mcp_reticle/bin/darwin-aarch64/reticle
mcp_reticle/bin/darwin-x86_64/reticle
mcp_reticle/bin/linux-aarch64/reticle
mcp_reticle/bin/linux-x86_64/reticle
mcp_reticle-0.1.0rc7.dist-info/METADATA
mcp_reticle-0.1.0rc7.dist-info/WHEEL
mcp_reticle-0.1.0rc7.dist-info/entry_points.txt
mcp_reticle-0.1.0rc7.dist-info/RECORD
