Metadata-Version: 2.4
Name: mcp-reticle
Version: 0.1.0rc7
Summary: Real-time debugging proxy for MCP (Model Context Protocol) servers
Project-URL: Homepage, https://github.com/labterminal/mcp-reticle
Project-URL: Repository, https://github.com/labterminal/mcp-reticle
Project-URL: Documentation, https://github.com/labterminal/mcp-reticle#readme
Author: Reticle Team
License-Expression: MIT
Keywords: ai,debugging,llm,mcp,model-context-protocol,proxy
Classifier: Development Status :: 4 - Beta
Classifier: Environment :: Console
Classifier: Intended Audience :: Developers
Classifier: Programming Language :: Python :: 3
Classifier: Programming Language :: Python :: 3.8
Classifier: Programming Language :: Python :: 3.9
Classifier: Programming Language :: Python :: 3.10
Classifier: Programming Language :: Python :: 3.11
Classifier: Programming Language :: Python :: 3.12
Classifier: Topic :: Software Development :: Debuggers
Requires-Python: >=3.8
